league/__init__.py
league/main.py
league/models.py
league/utils.py
python_league-0.0.6.dist-info/LICENSE
python_league-0.0.6.dist-info/METADATA
python_league-0.0.6.dist-info/WHEEL
python_league-0.0.6.dist-info/top_level.txt
python_league-0.0.6.dist-info/RECORD
