Metadata-Version: 2.1
Name: python-league
Version: 0.0.6
Summary: Python Wrapper of [League of Legends] | Riot API
Home-page: https://github.com/ah00ee/python-league
Author: ah00ee
Author-email: ah00ee.kr@gmail.com
License-File: LICENSE
Requires-Dist: requests
